setup.cfg
setup.py
pygrundig/__init__.py
pygrundig/pygrundig.py
pygrundig.egg-info/PKG-INFO
pygrundig.egg-info/SOURCES.txt
pygrundig.egg-info/dependency_links.txt
pygrundig.egg-info/requires.txt
pygrundig.egg-info/top_level.txt