Metadata-Version: 1.0
Name: pygrundig
Version: 0.0.1
Summary: Python library for controlling grundig smart tv's
Home-page: https://github.com/jpbede/pygrundig
Author: Jan-Philipp Benecke
Author-email: jan-philipp.benecke@jpbe.de
License: MIT
Platform: UNKNOWN
